{
    "url": "https://api.github.com/repos/dask/dask/issues/6405",
    "repository_url": "https://api.github.com/repos/dask/dask",
    "labels_url": "https://api.github.com/repos/dask/dask/issues/6405/labels{/name}",
    "comments_url": "https://api.github.com/repos/dask/dask/issues/6405/comments",
    "events_url": "https://api.github.com/repos/dask/dask/issues/6405/events",
    "html_url": "https://github.com/dask/dask/pull/6405",
    "id": 655264338,
    "node_id": "MDExOlB1bGxSZXF1ZXN0NDQ3ODA2NTM3",
    "number": 6405,
    "title": "Allow the deferral of array.to_hdf5",
    "user": {
        "login": "owena11",
        "id": 3437812,
        "node_id": "MDQ6VXNlcjM0Mzc4MTI=",
        "avatar_url": "https://avatars.githubusercontent.com/u/3437812?v=4",
        "gravatar_id": "",
        "url": "https://api.github.com/users/owena11",
        "html_url": "https://github.com/owena11",
        "followers_url": "https://api.github.com/users/owena11/followers",
        "following_url": "https://api.github.com/users/owena11/following{/other_user}",
        "gists_url": "https://api.github.com/users/owena11/gists{/gist_id}",
        "starred_url": "https://api.github.com/users/owena11/starred{/owner}{/repo}",
        "subscriptions_url": "https://api.github.com/users/owena11/subscriptions",
        "organizations_url": "https://api.github.com/users/owena11/orgs",
        "repos_url": "https://api.github.com/users/owena11/repos",
        "events_url": "https://api.github.com/users/owena11/events{/privacy}",
        "received_events_url": "https://api.github.com/users/owena11/received_events",
        "type": "User",
        "site_admin": false
    },
    "labels": [],
    "state": "open",
    "locked": false,
    "assignee": null,
    "assignees": [],
    "milestone": null,
    "comments": 6,
    "created_at": "2020-07-11T19:19:25Z",
    "updated_at": "2021-09-27T15:24:00Z",
    "closed_at": null,
    "author_association": "FIRST_TIME_CONTRIBUTOR",
    "active_lock_reason": null,
    "draft": false,
    "pull_request": {
        "url": "https://api.github.com/repos/dask/dask/pulls/6405",
        "html_url": "https://github.com/dask/dask/pull/6405",
        "diff_url": "https://github.com/dask/dask/pull/6405.diff",
        "patch_url": "https://github.com/dask/dask/pull/6405.patch",
        "merged_at": null
    },
    "body": "Attempted as a first issue.\r\n\r\nThe use of the context manager within the `.to_hdf5` prevents matching the behaviour exactly of the other save functions (eg. to_zarr) just passing through the `compute` flag through to the store operation,  so structured as a deferred call to the whole block. Might not be worth the special case for the benefit provides. \r\n\r\n- [x] Tests added / passed\r\n- [x] Passes `black dask` / `flake8 dask`\r\n\r\n\r\ncloses #1296",
    "closed_by": null,
    "reactions": {
        "url": "https://api.github.com/repos/dask/dask/issues/6405/reactions",
        "total_count": 0,
        "+1": 0,
        "-1": 0,
        "laugh": 0,
        "hooray": 0,
        "confused": 0,
        "heart": 0,
        "rocket": 0,
        "eyes": 0
    },
    "timeline_url": "https://api.github.com/repos/dask/dask/issues/6405/timeline",
    "performed_via_github_app": null,
    "state_reason": null
}