{
    "login": "smackesey",
    "id": 1531373,
    "node_id": "MDQ6VXNlcjE1MzEzNzM=",
    "avatar_url": "https://avatars.githubusercontent.com/u/1531373?v=4",
    "gravatar_id": "",
    "url": "https://api.github.com/users/smackesey",
    "html_url": "https://github.com/smackesey",
    "followers_url": "https://api.github.com/users/smackesey/followers",
    "following_url": "https://api.github.com/users/smackesey/following{/other_user}",
    "gists_url": "https://api.github.com/users/smackesey/gists{/gist_id}",
    "starred_url": "https://api.github.com/users/smackesey/starred{/owner}{/repo}",
    "subscriptions_url": "https://api.github.com/users/smackesey/subscriptions",
    "organizations_url": "https://api.github.com/users/smackesey/orgs",
    "repos_url": "https://api.github.com/users/smackesey/repos",
    "events_url": "https://api.github.com/users/smackesey/events{/privacy}",
    "received_events_url": "https://api.github.com/users/smackesey/received_events",
    "type": "User",
    "site_admin": false,
    "name": "Sean Mackesey",
    "company": "Dagster Labs",
    "blog": "",
    "location": "Reston, VA",
    "email": "s.mackesey@gmail.com",
    "hireable": null,
    "bio": null,
    "twitter_username": null,
    "public_repos": 29,
    "public_gists": 13,
    "followers": 14,
    "following": 0,
    "created_at": "2012-03-13T03:17:35Z",
    "updated_at": "2024-04-29T20:42:37Z"
}