{
    "login": "Crispy13",
    "id": 47196430,
    "node_id": "MDQ6VXNlcjQ3MTk2NDMw",
    "avatar_url": "https://avatars.githubusercontent.com/u/47196430?v=4",
    "gravatar_id": "",
    "url": "https://api.github.com/users/Crispy13",
    "html_url": "https://github.com/Crispy13",
    "followers_url": "https://api.github.com/users/Crispy13/followers",
    "following_url": "https://api.github.com/users/Crispy13/following{/other_user}",
    "gists_url": "https://api.github.com/users/Crispy13/gists{/gist_id}",
    "starred_url": "https://api.github.com/users/Crispy13/starred{/owner}{/repo}",
    "subscriptions_url": "https://api.github.com/users/Crispy13/subscriptions",
    "organizations_url": "https://api.github.com/users/Crispy13/orgs",
    "repos_url": "https://api.github.com/users/Crispy13/repos",
    "events_url": "https://api.github.com/users/Crispy13/events{/privacy}",
    "received_events_url": "https://api.github.com/users/Crispy13/received_events",
    "type": "User",
    "site_admin": false,
    "name": null,
    "company": null,
    "blog": "",
    "location": "South Korea",
    "email": null,
    "hireable": null,
    "bio": "Bioinformatics",
    "twitter_username": null,
    "public_repos": 16,
    "public_gists": 2,
    "followers": 3,
    "following": 5,
    "created_at": "2019-01-30T22:48:41Z",
    "updated_at": "2024-06-02T23:12:19Z"
}