{
    "login": "LeilaGold",
    "id": 60102289,
    "node_id": "MDQ6VXNlcjYwMTAyMjg5",
    "avatar_url": "https://avatars.githubusercontent.com/u/60102289?v=4",
    "gravatar_id": "",
    "url": "https://api.github.com/users/LeilaGold",
    "html_url": "https://github.com/LeilaGold",
    "followers_url": "https://api.github.com/users/LeilaGold/followers",
    "following_url": "https://api.github.com/users/LeilaGold/following{/other_user}",
    "gists_url": "https://api.github.com/users/LeilaGold/gists{/gist_id}",
    "starred_url": "https://api.github.com/users/LeilaGold/starred{/owner}{/repo}",
    "subscriptions_url": "https://api.github.com/users/LeilaGold/subscriptions",
    "organizations_url": "https://api.github.com/users/LeilaGold/orgs",
    "repos_url": "https://api.github.com/users/LeilaGold/repos",
    "events_url": "https://api.github.com/users/LeilaGold/events{/privacy}",
    "received_events_url": "https://api.github.com/users/LeilaGold/received_events",
    "type": "User",
    "site_admin": false,
    "name": "LeilaGold",
    "company": null,
    "blog": "",
    "location": "Rome",
    "email": null,
    "hireable": null,
    "bio": null,
    "twitter_username": null,
    "public_repos": 2,
    "public_gists": 0,
    "followers": 0,
    "following": 0,
    "created_at": "2020-01-20T13:54:48Z",
    "updated_at": "2020-09-30T08:42:43Z"
}