{
    "login": "FredericOdermatt",
    "id": 50372080,
    "node_id": "MDQ6VXNlcjUwMzcyMDgw",
    "avatar_url": "https://avatars.githubusercontent.com/u/50372080?v=4",
    "gravatar_id": "",
    "url": "https://api.github.com/users/FredericOdermatt",
    "html_url": "https://github.com/FredericOdermatt",
    "followers_url": "https://api.github.com/users/FredericOdermatt/followers",
    "following_url": "https://api.github.com/users/FredericOdermatt/following{/other_user}",
    "gists_url": "https://api.github.com/users/FredericOdermatt/gists{/gist_id}",
    "starred_url": "https://api.github.com/users/FredericOdermatt/starred{/owner}{/repo}",
    "subscriptions_url": "https://api.github.com/users/FredericOdermatt/subscriptions",
    "organizations_url": "https://api.github.com/users/FredericOdermatt/orgs",
    "repos_url": "https://api.github.com/users/FredericOdermatt/repos",
    "events_url": "https://api.github.com/users/FredericOdermatt/events{/privacy}",
    "received_events_url": "https://api.github.com/users/FredericOdermatt/received_events",
    "type": "User",
    "site_admin": false,
    "name": null,
    "company": "ETH Z\u00fcrich",
    "blog": "",
    "location": "Z\u00fcrich, Switzerland",
    "email": null,
    "hireable": null,
    "bio": "Information Technology student at ETH Zurich",
    "twitter_username": null,
    "public_repos": 15,
    "public_gists": 0,
    "followers": 4,
    "following": 5,
    "created_at": "2019-05-07T14:42:48Z",
    "updated_at": "2024-04-20T06:50:39Z"
}