[
    {
        "url": "https://api.github.com/repos/dask/dask/issues/comments/332541816",
        "html_url": "https://github.com/dask/dask/issues/2721#issuecomment-332541816",
        "issue_url": "https://api.github.com/repos/dask/dask/issues/2721",
        "id": 332541816,
        "node_id": "MDEyOklzc3VlQ29tbWVudDMzMjU0MTgxNg==",
        "user": {
            "login": "jakirkham",
            "id": 3019665,
            "node_id": "MDQ6VXNlcjMwMTk2NjU=",
            "avatar_url": "https://avatars.githubusercontent.com/u/3019665?v=4",
            "gravatar_id": "",
            "url": "https://api.github.com/users/jakirkham",
            "html_url": "https://github.com/jakirkham",
            "followers_url": "https://api.github.com/users/jakirkham/followers",
            "following_url": "https://api.github.com/users/jakirkham/following{/other_user}",
            "gists_url": "https://api.github.com/users/jakirkham/gists{/gist_id}",
            "starred_url": "https://api.github.com/users/jakirkham/starred{/owner}{/repo}",
            "subscriptions_url": "https://api.github.com/users/jakirkham/subscriptions",
            "organizations_url": "https://api.github.com/users/jakirkham/orgs",
            "repos_url": "https://api.github.com/users/jakirkham/repos",
            "events_url": "https://api.github.com/users/jakirkham/events{/privacy}",
            "received_events_url": "https://api.github.com/users/jakirkham/received_events",
            "type": "User",
            "site_admin": false
        },
        "created_at": "2017-09-27T14:35:00Z",
        "updated_at": "2017-09-27T14:35:00Z",
        "author_association": "MEMBER",
        "body": "Would be curious to hear any thoughts that @TomAugspurger or @bmerry have on the subject. Given both of you have navigated scalars and 0D arrays with Dask recently.",
        "reactions": {
            "url": "https://api.github.com/repos/dask/dask/issues/comments/332541816/reactions",
            "total_count": 0,
            "+1": 0,
            "-1": 0,
            "laugh": 0,
            "hooray": 0,
            "confused": 0,
            "heart": 0,
            "rocket": 0,
            "eyes": 0
        },
        "performed_via_github_app": null
    },
    {
        "url": "https://api.github.com/repos/dask/dask/issues/comments/332572053",
        "html_url": "https://github.com/dask/dask/issues/2721#issuecomment-332572053",
        "issue_url": "https://api.github.com/repos/dask/dask/issues/2721",
        "id": 332572053,
        "node_id": "MDEyOklzc3VlQ29tbWVudDMzMjU3MjA1Mw==",
        "user": {
            "login": "bmerry",
            "id": 1963944,
            "node_id": "MDQ6VXNlcjE5NjM5NDQ=",
            "avatar_url": "https://avatars.githubusercontent.com/u/1963944?v=4",
            "gravatar_id": "",
            "url": "https://api.github.com/users/bmerry",
            "html_url": "https://github.com/bmerry",
            "followers_url": "https://api.github.com/users/bmerry/followers",
            "following_url": "https://api.github.com/users/bmerry/following{/other_user}",
            "gists_url": "https://api.github.com/users/bmerry/gists{/gist_id}",
            "starred_url": "https://api.github.com/users/bmerry/starred{/owner}{/repo}",
            "subscriptions_url": "https://api.github.com/users/bmerry/subscriptions",
            "organizations_url": "https://api.github.com/users/bmerry/orgs",
            "repos_url": "https://api.github.com/users/bmerry/repos",
            "events_url": "https://api.github.com/users/bmerry/events{/privacy}",
            "received_events_url": "https://api.github.com/users/bmerry/received_events",
            "type": "User",
            "site_admin": false
        },
        "created_at": "2017-09-27T16:05:30Z",
        "updated_at": "2017-09-27T16:05:30Z",
        "author_association": "MEMBER",
        "body": "I don't think there is such a thing as a \"dask array scalar\". You can have dask 0-d arrays, but they're not scalars, and unlikely numpy 0-d arrays, they don't behave like scalars when it comes to type promotion.\r\n\r\nSo I guess one could have a `da.isscalar` that is just an alias of `np.isscalar`. Not sure how valuable that is.",
        "reactions": {
            "url": "https://api.github.com/repos/dask/dask/issues/comments/332572053/reactions",
            "total_count": 0,
            "+1": 0,
            "-1": 0,
            "laugh": 0,
            "hooray": 0,
            "confused": 0,
            "heart": 0,
            "rocket": 0,
            "eyes": 0
        },
        "performed_via_github_app": null
    },
    {
        "url": "https://api.github.com/repos/dask/dask/issues/comments/332577339",
        "html_url": "https://github.com/dask/dask/issues/2721#issuecomment-332577339",
        "issue_url": "https://api.github.com/repos/dask/dask/issues/2721",
        "id": 332577339,
        "node_id": "MDEyOklzc3VlQ29tbWVudDMzMjU3NzMzOQ==",
        "user": {
            "login": "jakirkham",
            "id": 3019665,
            "node_id": "MDQ6VXNlcjMwMTk2NjU=",
            "avatar_url": "https://avatars.githubusercontent.com/u/3019665?v=4",
            "gravatar_id": "",
            "url": "https://api.github.com/users/jakirkham",
            "html_url": "https://github.com/jakirkham",
            "followers_url": "https://api.github.com/users/jakirkham/followers",
            "following_url": "https://api.github.com/users/jakirkham/following{/other_user}",
            "gists_url": "https://api.github.com/users/jakirkham/gists{/gist_id}",
            "starred_url": "https://api.github.com/users/jakirkham/starred{/owner}{/repo}",
            "subscriptions_url": "https://api.github.com/users/jakirkham/subscriptions",
            "organizations_url": "https://api.github.com/users/jakirkham/orgs",
            "repos_url": "https://api.github.com/users/jakirkham/repos",
            "events_url": "https://api.github.com/users/jakirkham/events{/privacy}",
            "received_events_url": "https://api.github.com/users/jakirkham/received_events",
            "type": "User",
            "site_admin": false
        },
        "created_at": "2017-09-27T16:23:16Z",
        "updated_at": "2017-09-27T16:23:16Z",
        "author_association": "MEMBER",
        "body": "FWIU `np.isscalar` will trigger a computation. So aliasing is not an option.\r\n\r\nGuess we could check to see if the Dask Array is 0-D, but isn't it possible that could be a scalar or a 0-D array when computed? Is there some way to figure out which one it might be without computing the result?",
        "reactions": {
            "url": "https://api.github.com/repos/dask/dask/issues/comments/332577339/reactions",
            "total_count": 0,
            "+1": 0,
            "-1": 0,
            "laugh": 0,
            "hooray": 0,
            "confused": 0,
            "heart": 0,
            "rocket": 0,
            "eyes": 0
        },
        "performed_via_github_app": null
    },
    {
        "url": "https://api.github.com/repos/dask/dask/issues/comments/332582103",
        "html_url": "https://github.com/dask/dask/issues/2721#issuecomment-332582103",
        "issue_url": "https://api.github.com/repos/dask/dask/issues/2721",
        "id": 332582103,
        "node_id": "MDEyOklzc3VlQ29tbWVudDMzMjU4MjEwMw==",
        "user": {
            "login": "jcrist",
            "id": 2783717,
            "node_id": "MDQ6VXNlcjI3ODM3MTc=",
            "avatar_url": "https://avatars.githubusercontent.com/u/2783717?v=4",
            "gravatar_id": "",
            "url": "https://api.github.com/users/jcrist",
            "html_url": "https://github.com/jcrist",
            "followers_url": "https://api.github.com/users/jcrist/followers",
            "following_url": "https://api.github.com/users/jcrist/following{/other_user}",
            "gists_url": "https://api.github.com/users/jcrist/gists{/gist_id}",
            "starred_url": "https://api.github.com/users/jcrist/starred{/owner}{/repo}",
            "subscriptions_url": "https://api.github.com/users/jcrist/subscriptions",
            "organizations_url": "https://api.github.com/users/jcrist/orgs",
            "repos_url": "https://api.github.com/users/jcrist/repos",
            "events_url": "https://api.github.com/users/jcrist/events{/privacy}",
            "received_events_url": "https://api.github.com/users/jcrist/received_events",
            "type": "User",
            "site_admin": false
        },
        "created_at": "2017-09-27T16:39:48Z",
        "updated_at": "2017-09-27T16:39:48Z",
        "author_association": "MEMBER",
        "body": "> FWIU np.isscalar will trigger a computation. So aliasing is not an option.\r\n\r\nThis isn't true, it just checks the type of the argument. See the code [here](https://github.com/numpy/numpy/blob/master/numpy/core/numeric.py#L1934-L1963).\r\n\r\n> I don't think there is such a thing as a \"dask array scalar\". \r\n\r\nFor many operations numpy treats 0d arrays and scalars the same, and so for simplicity dask implemented scalars only as 0d dask arrays (one less class for us to worry about).\r\n\r\nI guess the question is, what do you need this operation for? If you're checking if it's a scalar-like, then checking if it's only 0d may be good enough. If you care about the distinction between 0d arrays and instances of `np.generic`, then this is not currently possible using dask.",
        "reactions": {
            "url": "https://api.github.com/repos/dask/dask/issues/comments/332582103/reactions",
            "total_count": 0,
            "+1": 0,
            "-1": 0,
            "laugh": 0,
            "hooray": 0,
            "confused": 0,
            "heart": 0,
            "rocket": 0,
            "eyes": 0
        },
        "performed_via_github_app": null
    },
    {
        "url": "https://api.github.com/repos/dask/dask/issues/comments/349150270",
        "html_url": "https://github.com/dask/dask/issues/2721#issuecomment-349150270",
        "issue_url": "https://api.github.com/repos/dask/dask/issues/2721",
        "id": 349150270,
        "node_id": "MDEyOklzc3VlQ29tbWVudDM0OTE1MDI3MA==",
        "user": {
            "login": "jakirkham",
            "id": 3019665,
            "node_id": "MDQ6VXNlcjMwMTk2NjU=",
            "avatar_url": "https://avatars.githubusercontent.com/u/3019665?v=4",
            "gravatar_id": "",
            "url": "https://api.github.com/users/jakirkham",
            "html_url": "https://github.com/jakirkham",
            "followers_url": "https://api.github.com/users/jakirkham/followers",
            "following_url": "https://api.github.com/users/jakirkham/following{/other_user}",
            "gists_url": "https://api.github.com/users/jakirkham/gists{/gist_id}",
            "starred_url": "https://api.github.com/users/jakirkham/starred{/owner}{/repo}",
            "subscriptions_url": "https://api.github.com/users/jakirkham/subscriptions",
            "organizations_url": "https://api.github.com/users/jakirkham/orgs",
            "repos_url": "https://api.github.com/users/jakirkham/repos",
            "events_url": "https://api.github.com/users/jakirkham/events{/privacy}",
            "received_events_url": "https://api.github.com/users/jakirkham/received_events",
            "type": "User",
            "site_admin": false
        },
        "created_at": "2017-12-05T00:07:24Z",
        "updated_at": "2017-12-05T00:07:24Z",
        "author_association": "MEMBER",
        "body": "Well some things like `min` actually do return a scalar when computed. Whereas slicing a Dask Array down to a single element returns a 0-D array. So the situation doesn't seem that cut and dry to me. Hence the interest in an `isscalar` check for Dask Arrays.",
        "reactions": {
            "url": "https://api.github.com/repos/dask/dask/issues/comments/349150270/reactions",
            "total_count": 0,
            "+1": 0,
            "-1": 0,
            "laugh": 0,
            "hooray": 0,
            "confused": 0,
            "heart": 0,
            "rocket": 0,
            "eyes": 0
        },
        "performed_via_github_app": null
    },
    {
        "url": "https://api.github.com/repos/dask/dask/issues/comments/349173798",
        "html_url": "https://github.com/dask/dask/issues/2721#issuecomment-349173798",
        "issue_url": "https://api.github.com/repos/dask/dask/issues/2721",
        "id": 349173798,
        "node_id": "MDEyOklzc3VlQ29tbWVudDM0OTE3Mzc5OA==",
        "user": {
            "login": "shoyer",
            "id": 1217238,
            "node_id": "MDQ6VXNlcjEyMTcyMzg=",
            "avatar_url": "https://avatars.githubusercontent.com/u/1217238?v=4",
            "gravatar_id": "",
            "url": "https://api.github.com/users/shoyer",
            "html_url": "https://github.com/shoyer",
            "followers_url": "https://api.github.com/users/shoyer/followers",
            "following_url": "https://api.github.com/users/shoyer/following{/other_user}",
            "gists_url": "https://api.github.com/users/shoyer/gists{/gist_id}",
            "starred_url": "https://api.github.com/users/shoyer/starred{/owner}{/repo}",
            "subscriptions_url": "https://api.github.com/users/shoyer/subscriptions",
            "organizations_url": "https://api.github.com/users/shoyer/orgs",
            "repos_url": "https://api.github.com/users/shoyer/repos",
            "events_url": "https://api.github.com/users/shoyer/events{/privacy}",
            "received_events_url": "https://api.github.com/users/shoyer/received_events",
            "type": "User",
            "site_admin": false
        },
        "created_at": "2017-12-05T02:20:25Z",
        "updated_at": "2017-12-05T02:20:25Z",
        "author_association": "MEMBER",
        "body": "> Well some things like min actually do return a scalar when computed.\r\n\r\nI would treat this as a bug. For consistency, every dask object should be an array when computed.",
        "reactions": {
            "url": "https://api.github.com/repos/dask/dask/issues/comments/349173798/reactions",
            "total_count": 0,
            "+1": 0,
            "-1": 0,
            "laugh": 0,
            "hooray": 0,
            "confused": 0,
            "heart": 0,
            "rocket": 0,
            "eyes": 0
        },
        "performed_via_github_app": null
    }
]