[
    {
        "url": "https://api.github.com/repos/dask/dask/issues/comments/882976070",
        "html_url": "https://github.com/dask/dask/issues/7911#issuecomment-882976070",
        "issue_url": "https://api.github.com/repos/dask/dask/issues/7911",
        "id": 882976070,
        "node_id": "IC_kwDOAbcwm840oSVG",
        "user": {
            "login": "GenevieveBuckley",
            "id": 30920819,
            "node_id": "MDQ6VXNlcjMwOTIwODE5",
            "avatar_url": "https://avatars.githubusercontent.com/u/30920819?v=4",
            "gravatar_id": "",
            "url": "https://api.github.com/users/GenevieveBuckley",
            "html_url": "https://github.com/GenevieveBuckley",
            "followers_url": "https://api.github.com/users/GenevieveBuckley/followers",
            "following_url": "https://api.github.com/users/GenevieveBuckley/following{/other_user}",
            "gists_url": "https://api.github.com/users/GenevieveBuckley/gists{/gist_id}",
            "starred_url": "https://api.github.com/users/GenevieveBuckley/starred{/owner}{/repo}",
            "subscriptions_url": "https://api.github.com/users/GenevieveBuckley/subscriptions",
            "organizations_url": "https://api.github.com/users/GenevieveBuckley/orgs",
            "repos_url": "https://api.github.com/users/GenevieveBuckley/repos",
            "events_url": "https://api.github.com/users/GenevieveBuckley/events{/privacy}",
            "received_events_url": "https://api.github.com/users/GenevieveBuckley/received_events",
            "type": "User",
            "site_admin": false
        },
        "created_at": "2021-07-20T01:31:42Z",
        "updated_at": "2021-07-20T01:31:42Z",
        "author_association": "MEMBER",
        "body": "For the layers specifically, I used the `toposort` function to re-order them for the high level graph text representation.\r\n\r\nAre there lots of other places besides layers where this is noticeable?",
        "reactions": {
            "url": "https://api.github.com/repos/dask/dask/issues/comments/882976070/reactions",
            "total_count": 0,
            "+1": 0,
            "-1": 0,
            "laugh": 0,
            "hooray": 0,
            "confused": 0,
            "heart": 0,
            "rocket": 0,
            "eyes": 0
        },
        "performed_via_github_app": null
    },
    {
        "url": "https://api.github.com/repos/dask/dask/issues/comments/883004280",
        "html_url": "https://github.com/dask/dask/issues/7911#issuecomment-883004280",
        "issue_url": "https://api.github.com/repos/dask/dask/issues/7911",
        "id": 883004280,
        "node_id": "IC_kwDOAbcwm840oZN4",
        "user": {
            "login": "mrocklin",
            "id": 306380,
            "node_id": "MDQ6VXNlcjMwNjM4MA==",
            "avatar_url": "https://avatars.githubusercontent.com/u/306380?v=4",
            "gravatar_id": "",
            "url": "https://api.github.com/users/mrocklin",
            "html_url": "https://github.com/mrocklin",
            "followers_url": "https://api.github.com/users/mrocklin/followers",
            "following_url": "https://api.github.com/users/mrocklin/following{/other_user}",
            "gists_url": "https://api.github.com/users/mrocklin/gists{/gist_id}",
            "starred_url": "https://api.github.com/users/mrocklin/starred{/owner}{/repo}",
            "subscriptions_url": "https://api.github.com/users/mrocklin/subscriptions",
            "organizations_url": "https://api.github.com/users/mrocklin/orgs",
            "repos_url": "https://api.github.com/users/mrocklin/repos",
            "events_url": "https://api.github.com/users/mrocklin/events{/privacy}",
            "received_events_url": "https://api.github.com/users/mrocklin/received_events",
            "type": "User",
            "site_admin": false
        },
        "created_at": "2021-07-20T02:31:23Z",
        "updated_at": "2021-07-20T02:31:23Z",
        "author_association": "MEMBER",
        "body": "Heads up, some toposort implementations are also not deterministic.  There\nare many valid toposorts.\n\nOn Mon, Jul 19, 2021 at 6:31 PM Genevieve Buckley ***@***.***>\nwrote:\n\n> For the layers specifically, I used the toposort function to re-order\n> them for the high level graph text representation.\n>\n> Are there lots of other places besides layers where this is noticeable?\n>\n> \u2014\n> You are receiving this because you are subscribed to this thread.\n> Reply to this email directly, view it on GitHub\n> <https://github.com/dask/dask/issues/7911#issuecomment-882976070>, or\n> unsubscribe\n> <https://github.com/notifications/unsubscribe-auth/AACKZTGMXYV5EPALJ65ZCOLTYTGYTANCNFSM5AT3AMWA>\n> .\n>\n",
        "reactions": {
            "url": "https://api.github.com/repos/dask/dask/issues/comments/883004280/reactions",
            "total_count": 0,
            "+1": 0,
            "-1": 0,
            "laugh": 0,
            "hooray": 0,
            "confused": 0,
            "heart": 0,
            "rocket": 0,
            "eyes": 0
        },
        "performed_via_github_app": null
    },
    {
        "url": "https://api.github.com/repos/dask/dask/issues/comments/883004710",
        "html_url": "https://github.com/dask/dask/issues/7911#issuecomment-883004710",
        "issue_url": "https://api.github.com/repos/dask/dask/issues/7911",
        "id": 883004710,
        "node_id": "IC_kwDOAbcwm840oZUm",
        "user": {
            "login": "mrocklin",
            "id": 306380,
            "node_id": "MDQ6VXNlcjMwNjM4MA==",
            "avatar_url": "https://avatars.githubusercontent.com/u/306380?v=4",
            "gravatar_id": "",
            "url": "https://api.github.com/users/mrocklin",
            "html_url": "https://github.com/mrocklin",
            "followers_url": "https://api.github.com/users/mrocklin/followers",
            "following_url": "https://api.github.com/users/mrocklin/following{/other_user}",
            "gists_url": "https://api.github.com/users/mrocklin/gists{/gist_id}",
            "starred_url": "https://api.github.com/users/mrocklin/starred{/owner}{/repo}",
            "subscriptions_url": "https://api.github.com/users/mrocklin/subscriptions",
            "organizations_url": "https://api.github.com/users/mrocklin/orgs",
            "repos_url": "https://api.github.com/users/mrocklin/repos",
            "events_url": "https://api.github.com/users/mrocklin/events{/privacy}",
            "received_events_url": "https://api.github.com/users/mrocklin/received_events",
            "type": "User",
            "site_admin": false
        },
        "created_at": "2021-07-20T02:32:44Z",
        "updated_at": "2021-07-20T02:32:44Z",
        "author_association": "MEMBER",
        "body": "More generally, I wouldn't want us to use a different data structure just\nfor doctests.  However in some cases, like the HLG case above, it probably\ndoes make sense for us to be consistent.\n\nWith regards to unskipping doctests I wouldn't go too crazy here.  In some\ncases it's perfectly fine to skip doctests.  I would unskip them with\nintention, rather than in a blanket effort.\n\nOn Mon, Jul 19, 2021 at 7:31 PM Matthew Rocklin ***@***.***> wrote:\n\n> Heads up, some toposort implementations are also not deterministic.  There\n> are many valid toposorts.\n>\n> On Mon, Jul 19, 2021 at 6:31 PM Genevieve Buckley <\n> ***@***.***> wrote:\n>\n>> For the layers specifically, I used the toposort function to re-order\n>> them for the high level graph text representation.\n>>\n>> Are there lots of other places besides layers where this is noticeable?\n>>\n>> \u2014\n>> You are receiving this because you are subscribed to this thread.\n>> Reply to this email directly, view it on GitHub\n>> <https://github.com/dask/dask/issues/7911#issuecomment-882976070>, or\n>> unsubscribe\n>> <https://github.com/notifications/unsubscribe-auth/AACKZTGMXYV5EPALJ65ZCOLTYTGYTANCNFSM5AT3AMWA>\n>> .\n>>\n>\n",
        "reactions": {
            "url": "https://api.github.com/repos/dask/dask/issues/comments/883004710/reactions",
            "total_count": 0,
            "+1": 0,
            "-1": 0,
            "laugh": 0,
            "hooray": 0,
            "confused": 0,
            "heart": 0,
            "rocket": 0,
            "eyes": 0
        },
        "performed_via_github_app": null
    },
    {
        "url": "https://api.github.com/repos/dask/dask/issues/comments/883372798",
        "html_url": "https://github.com/dask/dask/issues/7911#issuecomment-883372798",
        "issue_url": "https://api.github.com/repos/dask/dask/issues/7911",
        "id": 883372798,
        "node_id": "IC_kwDOAbcwm840pzL-",
        "user": {
            "login": "jsignell",
            "id": 4806877,
            "node_id": "MDQ6VXNlcjQ4MDY4Nzc=",
            "avatar_url": "https://avatars.githubusercontent.com/u/4806877?v=4",
            "gravatar_id": "",
            "url": "https://api.github.com/users/jsignell",
            "html_url": "https://github.com/jsignell",
            "followers_url": "https://api.github.com/users/jsignell/followers",
            "following_url": "https://api.github.com/users/jsignell/following{/other_user}",
            "gists_url": "https://api.github.com/users/jsignell/gists{/gist_id}",
            "starred_url": "https://api.github.com/users/jsignell/starred{/owner}{/repo}",
            "subscriptions_url": "https://api.github.com/users/jsignell/subscriptions",
            "organizations_url": "https://api.github.com/users/jsignell/orgs",
            "repos_url": "https://api.github.com/users/jsignell/repos",
            "events_url": "https://api.github.com/users/jsignell/events{/privacy}",
            "received_events_url": "https://api.github.com/users/jsignell/received_events",
            "type": "User",
            "site_admin": false
        },
        "created_at": "2021-07-20T13:00:22Z",
        "updated_at": "2021-07-20T13:00:22Z",
        "author_association": "MEMBER",
        "body": "> More generally, I wouldn't want us to use a different data structure just\r\nfor doctests.  However in some cases, like the HLG case above, it probably\r\ndoes make sense for us to be consistent.\r\n\r\nOh yeah, I'm definitely not saying that we should do this if the only benefit is that the doctests run. But I do think that in this case the doctests have exposed an area that could be improved (which is hopefully what tests are for!).\r\n\r\n> With regards to unskipping doctests I wouldn't go too crazy here.  In some\r\ncases it's perfectly fine to skip doctests.  I would unskip them with\r\nintention, rather than in a blanket effort.\r\n\r\nI tend to disagree. When doctests are skipped they tend to get out of date or be incomplete examples and that can make things confusing for users. I think that skipping doctests should be the exception and people should be pushed to try to write runnable examples.",
        "reactions": {
            "url": "https://api.github.com/repos/dask/dask/issues/comments/883372798/reactions",
            "total_count": 0,
            "+1": 0,
            "-1": 0,
            "laugh": 0,
            "hooray": 0,
            "confused": 0,
            "heart": 0,
            "rocket": 0,
            "eyes": 0
        },
        "performed_via_github_app": null
    },
    {
        "url": "https://api.github.com/repos/dask/dask/issues/comments/883400355",
        "html_url": "https://github.com/dask/dask/issues/7911#issuecomment-883400355",
        "issue_url": "https://api.github.com/repos/dask/dask/issues/7911",
        "id": 883400355,
        "node_id": "IC_kwDOAbcwm840p56j",
        "user": {
            "login": "mrocklin",
            "id": 306380,
            "node_id": "MDQ6VXNlcjMwNjM4MA==",
            "avatar_url": "https://avatars.githubusercontent.com/u/306380?v=4",
            "gravatar_id": "",
            "url": "https://api.github.com/users/mrocklin",
            "html_url": "https://github.com/mrocklin",
            "followers_url": "https://api.github.com/users/mrocklin/followers",
            "following_url": "https://api.github.com/users/mrocklin/following{/other_user}",
            "gists_url": "https://api.github.com/users/mrocklin/gists{/gist_id}",
            "starred_url": "https://api.github.com/users/mrocklin/starred{/owner}{/repo}",
            "subscriptions_url": "https://api.github.com/users/mrocklin/subscriptions",
            "organizations_url": "https://api.github.com/users/mrocklin/orgs",
            "repos_url": "https://api.github.com/users/mrocklin/repos",
            "events_url": "https://api.github.com/users/mrocklin/events{/privacy}",
            "received_events_url": "https://api.github.com/users/mrocklin/received_events",
            "type": "User",
            "site_admin": false
        },
        "created_at": "2021-07-20T13:38:20Z",
        "updated_at": "2021-07-20T13:38:20Z",
        "author_association": "MEMBER",
        "body": "> I tend to disagree. When doctests are skipped they tend to get out of\ndate or be incomplete examples and that can make things confusing for\nusers. I think that skipping doctests should be the exception and people\nshould be pushed to try to write runnable examples.\n\nI agree.  But in many cases we skip things intentionally because they don't\nmake sense to run as doctests.  I wouldn't want a blind effort to unskip\ndoctests.\n\nOn Tue, Jul 20, 2021 at 6:00 AM Julia Signell ***@***.***>\nwrote:\n\n> More generally, I wouldn't want us to use a different data structure just\n> for doctests. However in some cases, like the HLG case above, it probably\n> does make sense for us to be consistent.\n>\n> Oh yeah, I'm definitely not saying that we should do this if the only\n> benefit is that the doctests run. But I do think that in this case the\n> doctests have exposed an area that could be improved (which is hopefully\n> what tests are for!).\n>\n> With regards to unskipping doctests I wouldn't go too crazy here. In some\n> cases it's perfectly fine to skip doctests. I would unskip them with\n> intention, rather than in a blanket effort.\n>\n> I tend to disagree. When doctests are skipped they tend to get out of date\n> or be incomplete examples and that can make things confusing for users. I\n> think that skipping doctests should be the exception and people should be\n> pushed to try to write runnable examples.\n>\n> \u2014\n> You are receiving this because you commented.\n> Reply to this email directly, view it on GitHub\n> <https://github.com/dask/dask/issues/7911#issuecomment-883372798>, or\n> unsubscribe\n> <https://github.com/notifications/unsubscribe-auth/AACKZTH5HZPUKS77A4PG6ELTYVXPFANCNFSM5AT3AMWA>\n> .\n>\n",
        "reactions": {
            "url": "https://api.github.com/repos/dask/dask/issues/comments/883400355/reactions",
            "total_count": 0,
            "+1": 0,
            "-1": 0,
            "laugh": 0,
            "hooray": 0,
            "confused": 0,
            "heart": 0,
            "rocket": 0,
            "eyes": 0
        },
        "performed_via_github_app": null
    },
    {
        "url": "https://api.github.com/repos/dask/dask/issues/comments/883446689",
        "html_url": "https://github.com/dask/dask/issues/7911#issuecomment-883446689",
        "issue_url": "https://api.github.com/repos/dask/dask/issues/7911",
        "id": 883446689,
        "node_id": "IC_kwDOAbcwm840qFOh",
        "user": {
            "login": "jsignell",
            "id": 4806877,
            "node_id": "MDQ6VXNlcjQ4MDY4Nzc=",
            "avatar_url": "https://avatars.githubusercontent.com/u/4806877?v=4",
            "gravatar_id": "",
            "url": "https://api.github.com/users/jsignell",
            "html_url": "https://github.com/jsignell",
            "followers_url": "https://api.github.com/users/jsignell/followers",
            "following_url": "https://api.github.com/users/jsignell/following{/other_user}",
            "gists_url": "https://api.github.com/users/jsignell/gists{/gist_id}",
            "starred_url": "https://api.github.com/users/jsignell/starred{/owner}{/repo}",
            "subscriptions_url": "https://api.github.com/users/jsignell/subscriptions",
            "organizations_url": "https://api.github.com/users/jsignell/orgs",
            "repos_url": "https://api.github.com/users/jsignell/repos",
            "events_url": "https://api.github.com/users/jsignell/events{/privacy}",
            "received_events_url": "https://api.github.com/users/jsignell/received_events",
            "type": "User",
            "site_admin": false
        },
        "created_at": "2021-07-20T14:37:48Z",
        "updated_at": "2021-07-20T14:37:48Z",
        "author_association": "MEMBER",
        "body": "Yeah I agree, not a blind effort, but maybe a good-faith attempt to unskip. I think there have been some doctests where the doctests are just skipped because of copy/pasting from other places in the code or maybe not knowing about some of the othe doctest comment options. @zzhengnan is working on this with what feels to me like a very sane approach.",
        "reactions": {
            "url": "https://api.github.com/repos/dask/dask/issues/comments/883446689/reactions",
            "total_count": 0,
            "+1": 0,
            "-1": 0,
            "laugh": 0,
            "hooray": 0,
            "confused": 0,
            "heart": 0,
            "rocket": 0,
            "eyes": 0
        },
        "performed_via_github_app": null
    },
    {
        "url": "https://api.github.com/repos/dask/dask/issues/comments/883452755",
        "html_url": "https://github.com/dask/dask/issues/7911#issuecomment-883452755",
        "issue_url": "https://api.github.com/repos/dask/dask/issues/7911",
        "id": 883452755,
        "node_id": "IC_kwDOAbcwm840qGtT",
        "user": {
            "login": "mrocklin",
            "id": 306380,
            "node_id": "MDQ6VXNlcjMwNjM4MA==",
            "avatar_url": "https://avatars.githubusercontent.com/u/306380?v=4",
            "gravatar_id": "",
            "url": "https://api.github.com/users/mrocklin",
            "html_url": "https://github.com/mrocklin",
            "followers_url": "https://api.github.com/users/mrocklin/followers",
            "following_url": "https://api.github.com/users/mrocklin/following{/other_user}",
            "gists_url": "https://api.github.com/users/mrocklin/gists{/gist_id}",
            "starred_url": "https://api.github.com/users/mrocklin/starred{/owner}{/repo}",
            "subscriptions_url": "https://api.github.com/users/mrocklin/subscriptions",
            "organizations_url": "https://api.github.com/users/mrocklin/orgs",
            "repos_url": "https://api.github.com/users/mrocklin/repos",
            "events_url": "https://api.github.com/users/mrocklin/events{/privacy}",
            "received_events_url": "https://api.github.com/users/mrocklin/received_events",
            "type": "User",
            "site_admin": false
        },
        "created_at": "2021-07-20T14:45:44Z",
        "updated_at": "2021-07-20T14:45:44Z",
        "author_association": "MEMBER",
        "body": "OK.  Grand\n\nOn Tue, Jul 20, 2021 at 7:37 AM Julia Signell ***@***.***>\nwrote:\n\n> Yeah I agree, not a blind effort, but maybe a good-faith attempt to\n> unskip. I think there have been some doctests where the doctests are just\n> skipped because of copy/pasting from other places in the code or maybe not\n> knowing about some of the othe doctest comment options. @zzhengnan\n> <https://github.com/zzhengnan> is working on this with what feels to me\n> like a very sane approach.\n>\n> \u2014\n> You are receiving this because you commented.\n> Reply to this email directly, view it on GitHub\n> <https://github.com/dask/dask/issues/7911#issuecomment-883446689>, or\n> unsubscribe\n> <https://github.com/notifications/unsubscribe-auth/AACKZTCAXZVF7QRQ3INHXDDTYWC4NANCNFSM5AT3AMWA>\n> .\n>\n",
        "reactions": {
            "url": "https://api.github.com/repos/dask/dask/issues/comments/883452755/reactions",
            "total_count": 0,
            "+1": 0,
            "-1": 0,
            "laugh": 0,
            "hooray": 0,
            "confused": 0,
            "heart": 0,
            "rocket": 0,
            "eyes": 0
        },
        "performed_via_github_app": null
    }
]